{
  "daily_buy_executed_count": 5,
  "today_date_for_buy_limit": "2025-05-22",
  "trading_status": {
    "389470": {
      "status": "BOUGHT",
      "bought_price": 44650.0,
      "bought_quantity": 3,
      "bought_time": "2025-05-22 13:27:34"
    }
  },
  "watchlist": {
    "389470": {
      "code": "389470",
      "stock_name": "인벤티지랩",
      "current_price": 42750.0,
      "yesterday_close_price": 44650.0,
      "strategy_state": "BOUGHT",
      "avg_buy_price": 44650.0,
      "total_buy_quantity": 3,
      "current_high_price_after_buy": 44950.0,
      "is_trailing_stop_active": false,
      "trailing_stop_partially_sold": false,
      "partial_take_profit_executed": false,
      "buy_completion_count": 1,
      "buy_timestamp": "2025-05-22 13:27:34"
    }
  },
  "trading_records": {
    "매수건수": 0,
    "매수금액": 0,
    "매도건수": 0,
    "매도금액": 0,
    "총손익금": 0,
    "이익건수": 0,
    "이익금액": 0,
    "손실건수": 0,
    "손실금액": 0
  },
  "last_snapshot_date": null,
  "saved_datetime": "2025-05-22 13:36:51"
}